{
  "lastUpdated": "2025-12-06T04:49:55.641Z",
  "actualTiebreaker": 172,
  "topRunScorers": {
    "eng": [
      {
        "name": "Joe Root",
        "runs": 146
      },
      {
        "name": "Harry Brook",
        "runs": 83
      },
      {
        "name": "Ollie Pope",
        "runs": 79
      },
      {
        "name": "Zak Crawley",
        "runs": 76
      },
      {
        "name": "Ben Duckett",
        "runs": 49
      }
    ],
    "aus": [
      {
        "name": "Travis Head",
        "runs": 177
      },
      {
        "name": "Marnus Labuschagne",
        "runs": 125
      },
      {
        "name": "Jake Weatherald",
        "runs": 95
      },
      {
        "name": "Alex Carey",
        "runs": 89
      },
      {
        "name": "Steve Smith",
        "runs": 80
      }
    ]
  },
  "topWicketTakers": {
    "eng": [
      {
        "name": "Ben Stokes",
        "wickets": 8
      },
      {
        "name": "Brydon Carse",
        "wickets": 8
      },
      {
        "name": "Jofra Archer",
        "wickets": 3
      },
      {
        "name": "Gus Atkinson",
        "wickets": 1
      },
      {
        "name": "Zak Crawley",
        "wickets": 0
      }
    ],
    "aus": [
      {
        "name": "Mitchell Starc",
        "wickets": 16
      },
      {
        "name": "Brendan Doggett",
        "wickets": 6
      },
      {
        "name": "Scott Boland",
        "wickets": 5
      },
      {
        "name": "Cameron Green",
        "wickets": 1
      },
      {
        "name": "Neser",
        "wickets": 1
      }
    ]
  }
}